<annotation>
	<folder>hello</folder>
	<filename>hello.a55681d8-7e4e-11ef-8bd1-1e00b9212426.jpg</filename>
	<path>/Users/edbertwidjaja/Downloads/RealTimeObjectDetection/Tensorflow/workspace/images/collectedImages/hello/hello.a55681d8-7e4e-11ef-8bd1-1e00b9212426.jpg</path>
	<source>
		<database>Unknown</database>
	</source>
	<size>
		<width>1280</width>
		<height>720</height>
		<depth>3</depth>
	</size>
	<segmented>0</segmented>
	<object>
		<name>none</name>
		<pose>Unspecified</pose>
		<truncated>1</truncated>
		<difficult>0</difficult>
		<bndbox>
			<xmin>287</xmin>
			<ymin>138</ymin>
			<xmax>1057</xmax>
			<ymax>720</ymax>
		</bndbox>
	</object>
</annotation>
